example_package_akash/__init__.py
example_package_akash/task.py
example_package_akash-0.0.1.dist-info/METADATA
example_package_akash-0.0.1.dist-info/WHEEL
example_package_akash-0.0.1.dist-info/licenses/LICENCE
example_package_akash-0.0.1.dist-info/RECORD
